agentic_ai_demo/__init__.py
agentic_ai_demo/__main__.py
agentic_ai_demo/server.py
agentic_ai_demo/templates/index.html
agentic_ai_device_analysis-1.0.1.dist-info/licenses/LICENSE
agentic_ai_device_analysis-1.0.1.dist-info/METADATA
agentic_ai_device_analysis-1.0.1.dist-info/WHEEL
agentic_ai_device_analysis-1.0.1.dist-info/entry_points.txt
agentic_ai_device_analysis-1.0.1.dist-info/top_level.txt
agentic_ai_device_analysis-1.0.1.dist-info/RECORD
