Metadata-Version: 2.4
Name: agentic-ai-device-analysis
Version: 1.0.1
Summary: Agentic AI based Device Attributes Analysis Demo for fraud prevention
Home-page: https://github.com/deviceanalysis/agentic-ai-device-analysis
Author: Device Analysis Team
Author-email: Device Analysis Team <team@deviceanalysis.com>
Maintainer-email: Device Analysis Team <team@deviceanalysis.com>
License: MIT
Project-URL: Homepage, https://github.com/deviceanalysis/agentic-ai-device-analysis
Project-URL: Documentation, https://github.com/deviceanalysis/agentic-ai-device-analysis/wiki
Project-URL: Repository, https://github.com/deviceanalysis/agentic-ai-device-analysis.git
Project-URL: Bug Tracker, https://github.com/deviceanalysis/agentic-ai-device-analysis/issues
Keywords: agentic-ai,device-analysis,fraud-prevention,behavior-analysis,security,ai-demo
Classifier: Development Status :: 4 - Beta
Classifier: Intended Audience :: Developers
Classifier: Intended Audience :: Financial and Insurance Industry
Classifier: Intended Audience :: Information Technology
Classifier: Topic :: Software Development :: Libraries :: Python Modules
Classifier: Topic :: Security
Classifier: Topic :: Scientific/Engineering :: Artificial Intelligence
Classifier: Topic :: Internet :: WWW/HTTP :: HTTP Servers
Classifier: License :: OSI Approved :: MIT License
Classifier: Programming Language :: Python :: 3
Classifier: Programming Language :: Python :: 3.8
Classifier: Programming Language :: Python :: 3.9
Classifier: Programming Language :: Python :: 3.10
Classifier: Programming Language :: Python :: 3.11
Classifier: Programming Language :: Python :: 3.12
Classifier: Programming Language :: Python :: 3.13
Classifier: Operating System :: OS Independent
Requires-Python: >=3.8
License-File: LICENSE
Provides-Extra: dev
Requires-Dist: pytest>=6.0; extra == "dev"
Requires-Dist: black>=21.0; extra == "dev"
Requires-Dist: flake8>=3.8; extra == "dev"
Requires-Dist: mypy>=0.910; extra == "dev"
Requires-Dist: pre-commit>=2.15.0; extra == "dev"
Provides-Extra: test
Requires-Dist: pytest>=6.0; extra == "test"
Requires-Dist: pytest-cov>=2.12.0; extra == "test"
Requires-Dist: pytest-mock>=3.6.0; extra == "test"
Dynamic: author
Dynamic: home-page
Dynamic: license-file
Dynamic: requires-python
